jsonstream.py
jsonstream-0.0.1.dist-info/LICENSE
jsonstream-0.0.1.dist-info/METADATA
jsonstream-0.0.1.dist-info/WHEEL
jsonstream-0.0.1.dist-info/top_level.txt
jsonstream-0.0.1.dist-info/RECORD
