Metadata-Version: 2.1
Name: jsonstream
Version: 0.0.1
Summary: Load multiple delimited JSON documents from a single string or file-like object.
Home-page: https://github.com/Dunes/json_stream
Author: Jack Hargreaves
License: MIT
Keywords: JSON stream load
Platform: UNKNOWN
Classifier: Programming Language :: Python :: 3
Classifier: License :: OSI Approved :: MIT License
Classifier: Operating System :: OS Independent
Requires-Python: >=3.6
